duanzhenyan/__init__.py
duanzhenyan/dzhen_num.py
duanzhenyan/e_commerce_coupon.py
dzhenyan-0.0.2.dist-info/LICENSE
dzhenyan-0.0.2.dist-info/METADATA
dzhenyan-0.0.2.dist-info/WHEEL
dzhenyan-0.0.2.dist-info/top_level.txt
dzhenyan-0.0.2.dist-info/RECORD
