Metadata-Version: 2.1
Name: dzhenyan
Version: 0.0.2
Summary: 'private tools classifiers'
Home-page: https://github.com/dzhenyan/dzhenpypi.git
Author: dzhenyan
Author-email: dzhenyan@163.com
License: UNKNOWN
Project-URL: Bug Tracker, https://github.com/dzhenyan/dzhenpypi/issues
Platform: UNKNOWN
Classifier: Programming Language :: Python :: 3
Classifier: License :: OSI Approved :: MIT License
Classifier: Operating System :: OS Independent
Requires-Python: >=3.6
License-File: LICENSE
